argentic/__init__.py
argentic/__main__.py
argentic/cli_client.py
argentic/main.py
argentic/core/__init__.py
argentic/core/client.py
argentic/core/decorators.py
argentic/core/logger.py
argentic/core/agent/__init__.py
argentic/core/agent/agent.py
argentic/core/graph/__init__.py
argentic/core/graph/state.py
argentic/core/graph/supervisor.py
argentic/core/llm/__init__.py
argentic/core/llm/llm_factory.py
argentic/core/llm/providers/__init__.py
argentic/core/llm/providers/base.py
argentic/core/llm/providers/google_gemini.py
argentic/core/llm/providers/llama_cpp_cli.py
argentic/core/llm/providers/llama_cpp_server.py
argentic/core/llm/providers/mock.py
argentic/core/llm/providers/ollama.py
argentic/core/messager/__init__.py
argentic/core/messager/messager.py
argentic/core/messager/protocols.py
argentic/core/messager/drivers/KafkaDriver.py
argentic/core/messager/drivers/MQTTDriver.md
argentic/core/messager/drivers/MQTTDriver.py
argentic/core/messager/drivers/RabbitMQDriver.py
argentic/core/messager/drivers/RedisDriver.py
argentic/core/messager/drivers/__init__.py
argentic/core/messager/drivers/base_definitions.py
argentic/core/messager/drivers/configs.py
argentic/core/protocol/__init__.py
argentic/core/protocol/chat_message.py
argentic/core/protocol/enums.py
argentic/core/protocol/message.py
argentic/core/protocol/task.py
argentic/core/protocol/tool.py
argentic/core/tools/__init__.py
argentic/core/tools/tool_base.py
argentic/core/tools/tool_manager.py
argentic/services/__init__.py
argentic/services/environment_tool_service.py
argentic/services/rag_tool_service.py
argentic/tools/__init__.py
argentic/tools/Environment/README.md
argentic/tools/Environment/__init__.py
argentic/tools/Environment/environment.py
argentic/tools/Environment/environment_config.yaml
argentic/tools/Environment/environment_tool.py
argentic/tools/Google/google_search_tool.py
argentic/tools/RAG/README.md
argentic/tools/RAG/__init__.py
argentic/tools/RAG/knowledge_base_tool.py
argentic/tools/RAG/rag.py
argentic-0.12.0.dist-info/METADATA
argentic-0.12.0.dist-info/WHEEL
argentic-0.12.0.dist-info/entry_points.txt
argentic-0.12.0.dist-info/licenses/LICENSE
argentic-0.12.0.dist-info/RECORD
