Metadata-Version: 2.4
Name: argentic
Version: 0.12.0
Author-email: Iurii <angkira0@gmail.com>
License: MIT
License-File: LICENSE
Keywords: ai,ai agent,chromadb,ollama,rag,sentence-transformers
Classifier: License :: OSI Approved :: MIT License
Classifier: Operating System :: OS Independent
Classifier: Programming Language :: Python :: 3.12
Requires-Python: >=3.11
Requires-Dist: aiomqtt>=2.4.0
Requires-Dist: chromadb<2,>=1.0.9
Requires-Dist: google-generativeai>=0.8.5
Requires-Dist: ollama<0.5,>=0.4.8
Requires-Dist: python-dotenv
Requires-Dist: pyyaml<7,>=6.0.2
Requires-Dist: requests<3,>=2.31.0
Requires-Dist: sentence-transformers<5,>=4.1.0
Requires-Dist: tenacity<10,>=9.0.0
Requires-Dist: yaspin>=3.2.0
Provides-Extra: dev
Requires-Dist: black<26,>=25.1.0; extra == 'dev'
Requires-Dist: build>=1.2.2.post1; extra == 'dev'
Requires-Dist: commitizen<5,>=4.8.3; extra == 'dev'
Requires-Dist: flake8>=7.2.0; extra == 'dev'
Requires-Dist: isort<7,>=6.0.1; extra == 'dev'
Requires-Dist: pre-commit<5,>=4.2.0; extra == 'dev'
Requires-Dist: pyrefly>=0.15.2; extra == 'dev'
Requires-Dist: pytest-asyncio<0.24,>=0.23.5; extra == 'dev'
Requires-Dist: pytest<9,>=8.4.1; extra == 'dev'
Requires-Dist: python-on-whales>=0.70.0; extra == 'dev'
Requires-Dist: twine<7,>=6.2.0; extra == 'dev'
Provides-Extra: docs
Requires-Dist: mkdocs-macros-plugin>=1.3.7; extra == 'docs'
Requires-Dist: mkdocs-material>=9.6.14; extra == 'docs'
Requires-Dist: mkdocs-same-dir>=0.1.3; extra == 'docs'
Requires-Dist: mkdocs>=1.6.0; extra == 'docs'
Requires-Dist: mkdocstrings[python]>=0.24; extra == 'docs'
Requires-Dist: pymdown-extensions>=10.0; extra == 'docs'
Provides-Extra: kafka
Requires-Dist: aiokafka>=0.12.0; extra == 'kafka'
Provides-Extra: rabbitmq
Requires-Dist: aio-pika>=9.5.5; extra == 'rabbitmq'
Provides-Extra: redis
Requires-Dist: aioredis>=2.0.1; extra == 'redis'
